{"m_authorName":"hiroki","m_projectNoteList":[{"m_noteId":"b5246f5e-0d93-457d-820c-b95431afdae2","m_isRootNote":false,"m_author":"hiroki","m_noteContent":"","m_createdDate":"05/14/2024 23:39:13","m_updatedDate":"05/14/2024 23:39:13","m_projectNoteId":"8cfef068-8f93-4ef2-a527-70cd123b7ed3"},{"m_noteId":"99ad9c7a-4273-41fd-b647-4db0d0261c36","m_isRootNote":false,"m_author":"hiroki","m_noteContent":"","m_createdDate":"05/14/2024 23:46:53","m_updatedDate":"05/14/2024 23:46:53","m_projectNoteId":"5acf4da1-aa3f-4e60-b10e-0904fa3ca54e"},{"m_noteId":"a621d29c-47fc-4488-b369-7da9a0e56b52","m_isRootNote":false,"m_author":"hiroki","m_noteContent":"","m_createdDate":"05/14/2024 23:48:39","m_updatedDate":"05/14/2024 23:48:39","m_projectNoteId":"3628ef8f-44f7-4891-b6c0-b98295ad115a"},{"m_noteId":"b72884d2-8e6e-4acf-81bd-1dbb9ae96105","m_isRootNote":false,"m_author":"hiroki","m_noteContent":"","m_createdDate":"05/14/2024 23:54:02","m_updatedDate":"05/14/2024 23:54:02","m_projectNoteId":"ee31dc5f-a20b-4653-bc33-ba27c32c41af"},{"m_noteId":"968121cc-967a-41e7-85ac-fbd2ea6d6ad7","m_isRootNote":false,"m_author":"hiroki","m_noteContent":"","m_createdDate":"05/15/2024 23:27:37","m_updatedDate":"05/15/2024 23:27:37","m_projectNoteId":"9bf4294b-bae9-4f0c-b634-8511b396ecb7"},{"m_noteId":"74edfe07-dcef-428e-8704-d58e4cc030c0","m_isRootNote":true,"m_author":"hiroki","m_noteContent":"","m_createdDate":"05/15/2024 23:29:45","m_updatedDate":"05/15/2024 23:29:45","m_projectNoteId":"26b29b4b-2c84-4a2a-a1a6-8017ca7b283e"},{"m_noteId":"cd5466c5-575d-42e2-877a-2b0b8827e359","m_isRootNote":false,"m_author":"hiroki","m_noteContent":"","m_createdDate":"05/16/2024 00:01:08","m_updatedDate":"05/16/2024 00:01:08","m_projectNoteId":"3eefec6a-2be4-48f0-8028-9904223a8703"},{"m_noteId":"80a95827-8187-43c4-98f7-9a27ea82a3f0","m_isRootNote":false,"m_author":"hiroki","m_noteContent":"","m_createdDate":"05/16/2024 00:05:32","m_updatedDate":"05/16/2024 00:05:32","m_projectNoteId":"26b29b4b-2c84-4a2a-a1a6-8017ca7b283e"},{"m_noteId":"fd243c44-fd4d-4f7e-90dd-f49b922bdf2b","m_isRootNote":false,"m_author":"hiroki","m_noteContent":"","m_createdDate":"05/16/2024 00:05:42","m_updatedDate":"05/16/2024 00:05:42","m_projectNoteId":"26b29b4b-2c84-4a2a-a1a6-8017ca7b283e"},{"m_noteId":"eb359f92-54c0-4967-b3a0-c8244fca28c0","m_isRootNote":false,"m_author":"hiroki","m_noteContent":"テストテキスト","m_createdDate":"05/16/2024 00:12:30","m_updatedDate":"05/16/2024 00:12:30","m_projectNoteId":"26b29b4b-2c84-4a2a-a1a6-8017ca7b283e"},{"m_noteId":"9ff445aa-3af5-4204-9c69-c56ad425a75d","m_isRootNote":false,"m_author":"hiroki","m_noteContent":"t\ne\ns\nt","m_createdDate":"05/16/2024 00:22:11","m_updatedDate":"05/16/2024 00:22:11","m_projectNoteId":"26b29b4b-2c84-4a2a-a1a6-8017ca7b283e"},{"m_noteId":"48d97585-7f33-4515-96ce-a7ca8288bd24","m_isRootNote":false,"m_author":"hiroki","m_noteContent":"t\ne\ns\nt","m_createdDate":"05/16/2024 00:29:22","m_updatedDate":"05/16/2024 00:29:22","m_projectNoteId":"26b29b4b-2c84-4a2a-a1a6-8017ca7b283e"},{"m_noteId":"c8bd5786-4ee2-47e2-afae-5ae05eebd543","m_isRootNote":false,"m_author":"hiroki","m_noteContent":"","m_createdDate":"05/16/2024 00:29:36","m_updatedDate":"05/16/2024 00:29:36","m_projectNoteId":"fba6e360-bb0b-445f-a37e-28f76c18942a"},{"m_noteId":"ae6c13ac-cbb6-4d69-bdea-b0744eeb4548","m_isRootNote":false,"m_author":"hiroki","m_noteContent":"test","m_createdDate":"05/16/2024 00:31:42","m_updatedDate":"05/16/2024 00:31:42","m_projectNoteId":"26b29b4b-2c84-4a2a-a1a6-8017ca7b283e"},{"m_noteId":"bec45696-336e-4fa2-9423-698e267d9f8c","m_isRootNote":false,"m_author":"hiroki","m_noteContent":"test","m_createdDate":"05/16/2024 00:32:42","m_updatedDate":"05/16/2024 00:32:42","m_projectNoteId":"26b29b4b-2c84-4a2a-a1a6-8017ca7b283e"},{"m_noteId":"3b9f84aa-62da-49d4-bfde-2132085baf2f","m_isRootNote":false,"m_author":"hiroki","m_noteContent":"last?","m_createdDate":"05/16/2024 00:35:35","m_updatedDate":"05/16/2024 00:35:35","m_projectNoteId":"26b29b4b-2c84-4a2a-a1a6-8017ca7b283e"},{"m_noteId":"e4ddf279-5d56-4e7b-894e-73b250707c42","m_isRootNote":false,"m_author":"hiroki","m_noteContent":"test","m_createdDate":"05/18/2024 10:57:19","m_updatedDate":"05/18/2024 10:57:19","m_projectNoteId":"26b29b4b-2c84-4a2a-a1a6-8017ca7b283e"},{"m_noteId":"7b574b97-a0d8-49c1-a4d4-e7d2aaae3228","m_isRootNote":false,"m_author":"hiroki","m_noteContent":"","m_createdDate":"05/18/2024 11:14:58","m_updatedDate":"05/18/2024 11:14:58","m_projectNoteId":"26b29b4b-2c84-4a2a-a1a6-8017ca7b283e"},{"m_noteId":"846a1d1f-51c2-4538-a4ab-5c3ce9b28f05","m_isRootNote":false,"m_author":"hiroki","m_noteContent":"","m_createdDate":"05/18/2024 11:27:27","m_updatedDate":"05/18/2024 11:27:27","m_projectNoteId":"26b29b4b-2c84-4a2a-a1a6-8017ca7b283e"},{"m_noteId":"a9726be7-5d44-4d33-8c83-82ce880626a7","m_isRootNote":false,"m_author":"hiroki","m_noteContent":"","m_createdDate":"05/18/2024 11:38:31","m_updatedDate":"05/18/2024 11:38:31","m_projectNoteId":"26b29b4b-2c84-4a2a-a1a6-8017ca7b283e"},{"m_noteId":"5748eddf-3883-4367-bedc-f33664b4af4e","m_isRootNote":false,"m_author":"hiroki","m_noteContent":"test","m_createdDate":"05/18/2024 11:43:44","m_updatedDate":"05/18/2024 11:43:44","m_projectNoteId":"26b29b4b-2c84-4a2a-a1a6-8017ca7b283e"},{"m_noteId":"1a11436c-5a57-4fd2-b8a5-40e54a6e4cf4","m_isRootNote":false,"m_author":"hiroki","m_noteContent":"test","m_createdDate":"05/18/2024 11:43:45","m_updatedDate":"05/18/2024 11:43:45","m_projectNoteId":"26b29b4b-2c84-4a2a-a1a6-8017ca7b283e"},{"m_noteId":"e70c2d85-d9ab-45a2-bfe0-e18fe3a44c0d","m_isRootNote":false,"m_author":"hiroki","m_noteContent":"","m_createdDate":"05/18/2024 11:45:58","m_updatedDate":"05/18/2024 11:45:58","m_projectNoteId":"26b29b4b-2c84-4a2a-a1a6-8017ca7b283e"},{"m_noteId":"9f8b43cb-01f8-465a-b7f9-6672c51b5dc1","m_isRootNote":false,"m_author":"hiroki","m_noteContent":"test","m_createdDate":"05/18/2024 11:50:04","m_updatedDate":"05/18/2024 11:50:04","m_projectNoteId":"26b29b4b-2c84-4a2a-a1a6-8017ca7b283e"},{"m_noteId":"ee1aa876-d7c5-4ac4-bc34-e4b674c1e086","m_isRootNote":false,"m_author":"hiroki","m_noteContent":"test","m_createdDate":"05/18/2024 11:50:22","m_updatedDate":"05/18/2024 11:50:22","m_projectNoteId":"26b29b4b-2c84-4a2a-a1a6-8017ca7b283e"},{"m_noteId":"eee8aefd-deae-455f-bffa-8099c4c15119","m_isRootNote":false,"m_author":"hiroki","m_noteContent":"testenter","m_createdDate":"05/18/2024 12:11:51","m_updatedDate":"05/18/2024 12:11:51","m_projectNoteId":"26b29b4b-2c84-4a2a-a1a6-8017ca7b283e"}]}